[
  {
    "id": 1,
    "name": "Metallica",
    "genre": "Trash Metal",
    "concertInTurkey": true
  },
  {
    "id": 2,
    "name": "Disturbed",
    "genre": "Nu Metal",
    "concertInTurkey": false
  },
  {
    "id": 3,
    "name": "Iron Maiden",
    "genre": "Trash Metal",
    "concertInTurkey": true
  },
  {
    "id": 4,
    "name": "Blind Guardian",
    "genre": "Power Metal",
    "concertInTurkey": true
  },
  {
    "id": 5,
    "name": "Rammstein",
    "genre": "Heavy Metal",
    "concertInTurkey": false
  }
]
